{
  "db_name": "SQLite",
  "query": "\n\t\tINSERT INTO instance_links (\n\t\t\tinstance_id,\n\t\t\tlink_kind,\n\t\t\tshared_instance_id,\n\t\t\tshared_instance_role,\n\t\t\tshared_instance_manager_id,\n\t\t\tshared_instance_server_manager_name,\n\t\t\tshared_instance_server_manager_icon_url,\n\t\t\tshared_instance_linked_user_id\n\t\t)\n\t\tVALUES (?, 'unmanaged', ?, ?, ?, ?, ?, ?)\n\t\tON CONFLICT (instance_id) DO UPDATE SET\n\t\t\tlink_kind = CASE\n\t\t\t\tWHEN excluded.shared_instance_id IS NULL\n\t\t\t\t\tAND instance_links.link_kind = 'shared_instance'\n\t\t\t\t\tTHEN 'unmanaged'\n\t\t\t\tELSE instance_links.link_kind\n\t\t\tEND,\n\t\t\tshared_instance_id = excluded.shared_instance_id,\n\t\t\tshared_instance_role = excluded.shared_instance_role,\n\t\t\tshared_instance_manager_id = excluded.shared_instance_manager_id,\n\t\t\tshared_instance_server_manager_name = excluded.shared_instance_server_manager_name,\n\t\t\tshared_instance_server_manager_icon_url = excluded.shared_instance_server_manager_icon_url,\n\t\t\tshared_instance_linked_user_id = excluded.shared_instance_linked_user_id\n\t\t",
  "describe": {
    "columns": [],
    "parameters": {
      "Right": 7
    },
    "nullable": []
  },
  "hash": "b9ce6ff27e3b4d62ff0ae2bed0d00cae0b4b758c0674ac81659ee9d86667f19c"
}
